homura/__init__.py
homura/liblog.py
homura/lr_scheduler.py
homura/optim.py
homura/register.py
homura/reporters.py
homura/trainers.py
homura/metrics/__init__.py
homura/metrics/commons.py
homura/metrics/generative.py
homura/metrics/segmentation.py
homura/modules/__init__.py
homura/modules/attention.py
homura/modules/discretization.py
homura/modules/ema.py
homura/modules/loss.py
homura/modules/functional/__init__.py
homura/modules/functional/attention.py
homura/modules/functional/discretizations.py
homura/modules/functional/grad_approximation.py
homura/modules/functional/knn.py
homura/modules/functional/loss.py
homura/utils/__init__.py
homura/utils/_mixin.py
homura/utils/backends.py
homura/utils/benchmarks.py
homura/utils/containers.py
homura/utils/distributed.py
homura/utils/environment.py
homura/utils/grad_tools.py
homura/utils/reproducibility.py
homura/vision/__init__.py
homura/vision/data/__init__.py
homura/vision/data/classification.py
homura/vision/data/detection.py
homura/vision/data/segmentation.py
homura/vision/data/statistics.py
homura/vision/data/visionset.py
homura/vision/models/__init__.py
homura/vision/models/_utils.py
homura/vision/models/cifar_resnet.py
homura/vision/models/densenet.py
homura/vision/models/unet.py
homura/vision/transforms/__init__.py
homura/vision/transforms/mixup.py
homura/vision/transforms/transform.py
tests/test_metrics/__init__.py
tests/test_metrics/test_commons.py
tests/test_metrics/test_segmentation.py
tests/test_utils/__init__.py
tests/test_utils/test_containers.py
tests/test_utils/test_reproducibility.py
tests/test_vision/__init__.py
tests/test_vision/test_mixup.py
tests/test_vision/test_models.py
tests/test_vision/test_transforms.py
tests/test_vision/test_data/__init__.py
tests/test_vision/test_data/test_statistics.py
homura_core-2021.12.1.dist-info/LICENSE
homura_core-2021.12.1.dist-info/METADATA
homura_core-2021.12.1.dist-info/WHEEL
homura_core-2021.12.1.dist-info/top_level.txt
homura_core-2021.12.1.dist-info/RECORD
