Metadata-Version: 2.1
Name: homura-core
Version: 2021.12.1
Summary: a fast prototyping library for DL research
Home-page: https://github.com/moskomule/homura
Author: Ryuichiro Hataya
Author-email: hataya@nlab-mpg.jp
License: Apache License 2.0
Platform: UNKNOWN
Requires-Python: >=3.9
License-File: LICENSE
Requires-Dist: torch (>=1.8.1)
Requires-Dist: torchvision (>=0.9.1)
Requires-Dist: tqdm
Requires-Dist: tensorboard
Requires-Dist: colorlog
